nbclassifier/__init__.py
nbclassifier/nbclassifier.py
nbclassifier-0.22.dist-info/METADATA
nbclassifier-0.22.dist-info/WHEEL
nbclassifier-0.22.dist-info/top_level.txt
nbclassifier-0.22.dist-info/RECORD
